quantes/PyPI-Recovery-Codes-wenxinz-2024-03-31T03_02_54.141117.txt
quantes/__init__.py
quantes/admm.py
quantes/composite.py
quantes/joint.py
quantes/linear.py
quantes/nonlinear.py
quantes/solvers.py
quantes/utils.py
quantes-2.0.8.dist-info/LICENSE
quantes-2.0.8.dist-info/METADATA
quantes-2.0.8.dist-info/WHEEL
quantes-2.0.8.dist-info/top_level.txt
quantes-2.0.8.dist-info/RECORD
