Metadata-Version: 2.1
Name: quantes
Version: 2.0.8
Summary: Convolution Smoothed Quantile and Expected Shortfall Regression
Home-page: https://github.com/WenxinZhou/quantes
Author: Wenxin Zhou
Author-email: wenxinz@uic.edu
Classifier: Programming Language :: Python :: 3
Classifier: License :: OSI Approved :: MIT License
Classifier: Operating System :: OS Independent
License-File: LICENSE
Requires-Dist: numpy
Requires-Dist: scipy
Requires-Dist: scikit-learn
Requires-Dist: qpsolvers
Requires-Dist: cvxopt
Requires-Dist: torch
Requires-Dist: matplotlib
